<?xml version="1.0" encoding="UTF-8"?>
<list xmlns:xsi="http://www.w3.org/2001/XMLSchema-instance" xsi:noNamespaceSchemaLocation="../../xsd/multisell.xsd">
	<npcs>
		<npc>-1</npc> <!-- Item Multisell -->
	</npcs>
	<!-- +9 Armor of Protection (Sealed) -->
	<item>
		<ingredient id="105094" count="1" /> <!-- +9 Armor of Protection Coupon (Sealed) (Time-limited) - Sealed -->
		<production id="105083" count="1" /> <!-- Package: +9 Breastplate of Protection (Sealed) - Sealed -->
	</item>
	<item>
		<ingredient id="105094" count="1" /> <!-- +9 Armor of Protection Coupon (Sealed) (Time-limited) - Sealed -->
		<production id="105084" count="1" /> <!-- Package: +9 Gaiters of Protection (Sealed) - Sealed -->
	</item>
	<item>
		<ingredient id="105094" count="1" /> <!-- +9 Armor of Protection Coupon (Sealed) (Time-limited) - Sealed -->
		<production id="105085" count="1" /> <!-- Package: +9 Leather Armor of Protection (Sealed) - Sealed -->
	</item>
	<item>
		<ingredient id="105094" count="1" /> <!-- +9 Armor of Protection Coupon (Sealed) (Time-limited) - Sealed -->
		<production id="105086" count="1" /> <!-- Package: +9 Leather Leggings of Protection (Sealed) - Sealed -->
	</item>
	<item>
		<ingredient id="105094" count="1" /> <!-- +9 Armor of Protection Coupon (Sealed) (Time-limited) - Sealed -->
		<production id="105087" count="1" /> <!-- Package: +9 Tunic of Protection (Sealed) - Sealed -->
	</item>
	<item>
		<ingredient id="105094" count="1" /> <!-- +9 Armor of Protection Coupon (Sealed) (Time-limited) - Sealed -->
		<production id="105088" count="1" /> <!-- Package: +9 Stockings of Protection (Sealed) - Sealed -->
	</item>
	<item>
		<ingredient id="105094" count="1" /> <!-- +9 Armor of Protection Coupon (Sealed) (Time-limited) - Sealed -->
		<production id="105089" count="1" /> <!-- Package: +9 Gauntlets of Protection (Sealed) - Sealed -->
	</item>
	<item>
		<ingredient id="105094" count="1" /> <!-- +9 Armor of Protection Coupon (Sealed) (Time-limited) - Sealed -->
		<production id="105090" count="1" /> <!-- Package: +9 Helmet of Protection (Sealed) - Sealed -->
	</item>
	<item>
		<ingredient id="105094" count="1" /> <!-- +9 Armor of Protection Coupon (Sealed) (Time-limited) - Sealed -->
		<production id="105091" count="1" /> <!-- Package: +9 Boots of Protection (Sealed) - Sealed -->
	</item>
</list>
